nons/README.md
nons/__init__.py
nons/core/README.md
nons/core/__init__.py
nons/core/config.py
nons/core/errors.py
nons/core/layer.py
nons/core/network.py
nons/core/node.py
nons/core/scheduler.py
nons/core/types.py
nons/core/agents/README.md
nons/core/agents/__init__.py
nons/core/agents/agent.py
nons/core/agents/registry.py
nons/observability/README.md
nons/observability/__init__.py
nons/observability/integration.py
nons/observability/logger.py
nons/observability/logging.py
nons/observability/metrics.py
nons/observability/tracer.py
nons/observability/tracing.py
nons/operators/README.md
nons/operators/__init__.py
nons/operators/base.py
nons/operators/custom.py
nons/operators/deterministic.py
nons/operators/registry.py
nons/runtime/__init__.py
nons/runtime/compiler.py
nons/runtime/executor.py
nons/utils/README.md
nons/utils/__init__.py
nons/utils/helpers.py
nons/utils/providers.py
nons-0.1.0.dist-info/METADATA
nons-0.1.0.dist-info/WHEEL
nons-0.1.0.dist-info/licenses/LICENSE
nons-0.1.0.dist-info/RECORD
