Metadata-Version: 2.4
Name: nons
Version: 0.1.0
Summary: Network of Networks (NoN): Building Optimized Compound AI Systems
Project-URL: Homepage, https://github.com/shreypjain/non
Project-URL: Repository, https://github.com/shreypjain/non
Project-URL: Documentation, https://github.com/shreypjain/non/tree/main/docs
Project-URL: Issues, https://github.com/shreypjain/non/issues
Author-email: NoN Contributors <shrey@lunchlinepartners.com>
Maintainer-email: NoN Contributors <shrey@lunchlinepartners.com>
License: MIT
License-File: LICENSE
Keywords: agents,ai,anthropic,compound-ai,google-gemini,llm,multi-model,network,openai,orchestration,prompt-engineering
Classifier: Development Status :: 3 - Alpha
Classifier: Intended Audience :: Developers
Classifier: Intended Audience :: Science/Research
Classifier: License :: OSI Approved :: MIT License
Classifier: Operating System :: OS Independent
Classifier: Programming Language :: Python :: 3
Classifier: Programming Language :: Python :: 3.9
Classifier: Programming Language :: Python :: 3.10
Classifier: Programming Language :: Python :: 3.11
Classifier: Programming Language :: Python :: 3.12
Classifier: Topic :: Scientific/Engineering :: Artificial Intelligence
Classifier: Topic :: Software Development :: Libraries :: Python Modules
Classifier: Typing :: Typed
Requires-Python: >=3.9
Requires-Dist: aiohttp>=3.8.0
Requires-Dist: anthropic>=0.7.0
Requires-Dist: asyncio-throttle>=1.0.0
Requires-Dist: google-genai>=0.1.0
Requires-Dist: openai>=1.0.0
Requires-Dist: pydantic>=2.0.0
Requires-Dist: python-dotenv>=1.1.1
Requires-Dist: structlog>=23.0.0
Requires-Dist: tenacity>=8.0.0
Requires-Dist: typing-extensions>=4.0.0
Provides-Extra: dev
Requires-Dist: black>=23.0.0; extra == 'dev'
Requires-Dist: mypy>=1.0.0; extra == 'dev'
Requires-Dist: pytest-asyncio>=0.21.0; extra == 'dev'
Requires-Dist: pytest-mock>=3.10.0; extra == 'dev'
Requires-Dist: pytest>=7.0.0; extra == 'dev'
Requires-Dist: ruff>=0.1.0; extra == 'dev'
